PCSAFTsuperanc.cpython-312-darwin.so
PCSAFTsuperanc-0.0.7.dist-info/LICENSE.md
PCSAFTsuperanc-0.0.7.dist-info/RECORD
PCSAFTsuperanc-0.0.7.dist-info/WHEEL
PCSAFTsuperanc-0.0.7.dist-info/top_level.txt
PCSAFTsuperanc-0.0.7.dist-info/METADATA
