Metadata-Version: 2.1
Name: PCSAFTsuperanc
Version: 0.0.7
Summary: Superancillary functions for the PC-SAFT EOS of Gross and Sadowski
Author: Ian Bell
Author-email: ian.bell@nist.gov
Requires-Python: >=3.6
License-File: LICENSE.md
Provides-Extra: test
Requires-Dist: pytest (>=6.0) ; extra == 'test'
